<?xml version="1.0" encoding="UTF-8"?>
<fbt_app>
  <name>GetSocial</name>
  <fbt_string locale="en_US" hash="0bdf421bf0b9ed72125e7520b9c9a8a8">
    <fbt_text><fbt_token name="name1"/><![CDATA[ and ]]><fbt_token name="name2"/><![CDATA[ had ]]><fbt_token name="product count products"/><![CDATA[.]]></fbt_text>
  </fbt_string>
  <fbt_string locale="en_US" hash="0f9a24808340d55640c2de2b5e3a3295">
    <fbt_text><fbt_token name="name"/><![CDATA[ had ]]><fbt_token name="number"/><![CDATA[ products.]]></fbt_text>
  </fbt_string>
  <fbt_string locale="en_US" hash="183d04f55bd9a43740bc5c5f44875c65">
    <fbt_text><fbt_token name="name"/><![CDATA[ had a product.]]></fbt_text>
  </fbt_string>
  <fbt_string locale="en_US" hash="1e56044b8a4372a6ada9c13e06096382">
    <fbt_text><fbt_token name="name1"/><![CDATA[ and ]]><fbt_token name="name count others"/><![CDATA[ had a product.]]></fbt_text>
  </fbt_string>
  <fbt_string locale="en_US" hash="208a3fb081ce6adf19dbefb1e31b524e">
    <fbt_text><![CDATA[a product you had]]></fbt_text>
  </fbt_string>
  <fbt_string locale="en_US" hash="20d3fd03b500f916c4339553ba7f1c0a">
    <fbt_text><fbt_token name="name1"/><![CDATA[ and ]]><fbt_token name="name count others"/><![CDATA[ had ]]><fbt_token name="product1"/><![CDATA[ and ]]><fbt_token name="product count other products"/><![CDATA[.]]></fbt_text>
  </fbt_string>
  <fbt_string locale="en_US" hash="229fc75b1ae97e4c9cedf4af86ff3d0f">
    <fbt_text><fbt_token name="name1"/><![CDATA[ had this.]]></fbt_text>
  </fbt_string>
  <fbt_string locale="en_US" hash="2d27f4d984dc2f84c2903b843710d107">
    <fbt_text><fbt_token name="name1"/><![CDATA[ had a product ]]><fbt_token name="sent_aux_a"/><![CDATA[ ]]><fbt_token name="sent_aux_b"/><![CDATA[ ]]><fbt_token name="sent_aux_c"/><![CDATA[.]]></fbt_text>
  </fbt_string>
  <fbt_string locale="en_US" hash="3347925f450647ddaf4c8e9639882641">
    <fbt_text><![CDATA[You and ]]><fbt_token name="number"/><![CDATA[ others had this.]]></fbt_text>
  </fbt_string>
  <fbt_string locale="en_US" hash="34b8804ac3f3d799472ff6c0f30d4ab0">
    <fbt_text><![CDATA[Had ]]><fbt_token name="product1"/><![CDATA[.]]></fbt_text>
  </fbt_string>
  <fbt_string locale="en_US" hash="36c5b872fc18cea96fb3e94f26dcf8e0">
    <fbt_text><fbt_token name="name1"/><![CDATA[ and ]]><fbt_token name="name2"/><![CDATA[ had this.]]></fbt_text>
  </fbt_string>
  <fbt_string locale="en_US" hash="3b522371a60fe3e7725ddcc743ecb423">
    <fbt_text><fbt_token name="name1"/><![CDATA[ had ]]><fbt_token name="product count products"/><![CDATA[ ]]><fbt_token name="sent_aux_a"/><![CDATA[ ]]><fbt_token name="sent_aux_b"/><![CDATA[ ]]><fbt_token name="sent_aux_c"/><![CDATA[.]]></fbt_text>
  </fbt_string>
  <fbt_string locale="en_US" hash="429277bfade16cd8d28b45e5cb408653">
    <fbt_text><![CDATA[products she had]]></fbt_text>
  </fbt_string>
  <fbt_string locale="en_US" hash="46007e274c9b36a47367816ee69dc722">
    <fbt_text><![CDATA[a product he had]]></fbt_text>
  </fbt_string>
  <fbt_string locale="en_US" hash="4b355ef91205d806fb75b1f8114ab86e">
    <fbt_text><![CDATA[products he had]]></fbt_text>
  </fbt_string>
  <fbt_string locale="en_US" hash="501a055da8b8e811f1502c515962accf">
    <fbt_text><fbt_token name="name1"/><![CDATA[ and ]]><fbt_token name="name count others"/><![CDATA[ had ]]><fbt_token name="product1"/><![CDATA[ ]]><fbt_token name="sent_aux_a"/><![CDATA[ ]]><fbt_token name="sent_aux_b"/><![CDATA[ ]]><fbt_token name="sent_aux_c"/><![CDATA[.]]></fbt_text>
  </fbt_string>
  <fbt_string locale="en_US" hash="5544ec72639c4c787d6aa69ae68c86af">
    <fbt_text><![CDATA[products they had]]></fbt_text>
  </fbt_string>
  <fbt_string locale="en_US" hash="5d40aeb1b44f7f7eb73cc6d404ab5f1b">
    <fbt_text><fbt_token name="name1"/><![CDATA[ and ]]><fbt_token name="name count others"/><![CDATA[ had ]]><fbt_token name="product count products"/><![CDATA[.]]></fbt_text>
  </fbt_string>
  <fbt_string locale="en_US" hash="64d89ec7b692efbf0cf25b8d36e118a5">
    <fbt_text><fbt_token name="number"/><![CDATA[ others had this. Be the first of your friends.]]></fbt_text>
  </fbt_string>
  <fbt_string locale="en_US" hash="65abf4471ebbfb75a111aae777e4bad4">
    <fbt_text><fbt_token name="name1"/><![CDATA[ and ]]><fbt_token name="name count others"/><![CDATA[ had a product ]]><fbt_token name="sent_aux_a"/><![CDATA[ ]]><fbt_token name="sent_aux_b"/><![CDATA[ ]]><fbt_token name="sent_aux_c"/><![CDATA[.]]></fbt_text>
  </fbt_string>
  <fbt_string locale="en_US" hash="678196e325635cb33b7b98aa225b87af">
    <fbt_text><![CDATA[products ]]><fbt_token name="name"/><![CDATA[ had]]></fbt_text>
  </fbt_string>
  <fbt_string locale="en_US" hash="6ee4dc90d6419d68afcca76f0c2bc154">
    <fbt_text><![CDATA[a product ]]><fbt_token name="name"/><![CDATA[ had]]></fbt_text>
  </fbt_string>
  <fbt_string locale="en_US" hash="6f91cc124c08ae65d1990d36ea05f84f">
    <fbt_text><fbt_token name="name1"/><![CDATA[ and ]]><fbt_token name="name count others"/><![CDATA[ had ]]><fbt_token name="product count products"/><![CDATA[ ]]><fbt_token name="sent_aux_a"/><![CDATA[ ]]><fbt_token name="sent_aux_b"/><![CDATA[ ]]><fbt_token name="sent_aux_c"/><![CDATA[.]]></fbt_text>
  </fbt_string>
  <fbt_string locale="en_US" hash="71517b8f5fe67f966ab137691755ef1f">
    <fbt_text><![CDATA[You and ]]><fbt_token name="name count"/><![CDATA[ others had this.]]></fbt_text>
  </fbt_string>
  <fbt_string locale="en_US" hash="7b7e015f904883929951daa183ebc5fb">
    <fbt_text><fbt_token name="name1"/><![CDATA[ and ]]><fbt_token name="name count"/><![CDATA[ others had this.]]></fbt_text>
  </fbt_string>
  <fbt_string locale="en_US" hash="8096d0c8339804034bfdf9f91d0d1f91">
    <fbt_text><![CDATA[You had this.]]></fbt_text>
  </fbt_string>
  <fbt_string locale="en_US" hash="85f7f12134509de23d81549f958e5e13">
    <fbt_text><fbt_token name="name1"/><![CDATA[ and ]]><fbt_token name="name2"/><![CDATA[ had ]]><fbt_token name="product1"/><![CDATA[ and ]]><fbt_token name="product2"/><![CDATA[.]]></fbt_text>
  </fbt_string>
  <fbt_string locale="en_US" hash="91dd1d8b37eee8e12578dcff0bed3f0f">
    <fbt_text><fbt_token name="name1"/><![CDATA[ had ]]><fbt_token name="product1"/><![CDATA[ ]]><fbt_token name="sent_aux_a"/><![CDATA[ ]]><fbt_token name="sent_aux_b"/><![CDATA[ ]]><fbt_token name="sent_aux_c"/><![CDATA[.]]></fbt_text>
  </fbt_string>
  <fbt_string locale="en_US" hash="934c6f973dd21f89508c5d89499de3aa">
    <fbt_text><![CDATA[You and 1 other had this.]]></fbt_text>
  </fbt_string>
  <fbt_string locale="en_US" hash="98259cd3d0c2b9430f7652e08b8a858e">
    <fbt_text><![CDATA[a product they had]]></fbt_text>
  </fbt_string>
  <fbt_string locale="en_US" hash="9cea7683c7d8706eb0cf6bd4d675bbd6">
    <fbt_text><fbt_token name="name1"/><![CDATA[ and ]]><fbt_token name="name2"/><![CDATA[ had a product ]]><fbt_token name="sent_aux_a"/><![CDATA[ ]]><fbt_token name="sent_aux_b"/><![CDATA[ ]]><fbt_token name="sent_aux_c"/><![CDATA[.]]></fbt_text>
  </fbt_string>
  <fbt_string locale="en_US" hash="9e9c10f5b943a923e9c1b6a263c49977">
    <fbt_text><![CDATA[1 other had this. Be the first of your friends.]]></fbt_text>
  </fbt_string>
  <fbt_string locale="en_US" hash="a03a9a2eadaf8adb9f11edc1947c0bb6">
    <fbt_text><fbt_token name="name1"/><![CDATA[ and ]]><fbt_token name="name count others"/><![CDATA[ had ]]><fbt_token name="product1"/><![CDATA[ and ]]><fbt_token name="product2"/><![CDATA[.]]></fbt_text>
  </fbt_string>
  <fbt_string locale="en_US" hash="a0a2c1628cb2111d28ee6886bd8ef331">
    <fbt_text><![CDATA[1 other had this.]]></fbt_text>
  </fbt_string>
  <fbt_string locale="en_US" hash="a540a07d7591db53cc7708879f214b21">
    <fbt_text><fbt_token name="name1"/><![CDATA[ and ]]><fbt_token name="name2"/><![CDATA[ had ]]><fbt_token name="product1"/><![CDATA[ ]]><fbt_token name="sent_aux_a"/><![CDATA[ ]]><fbt_token name="sent_aux_b"/><![CDATA[ ]]><fbt_token name="sent_aux_c"/><![CDATA[.]]></fbt_text>
  </fbt_string>
  <fbt_string locale="en_US" hash="a76ee18670412e5ec80385c4f3ee3291">
    <fbt_text><fbt_token name="name"/><![CDATA[ had ]]><fbt_token name="number"/><![CDATA[ products ]]><fbt_token name="sent_aux_a"/><![CDATA[ ]]><fbt_token name="sent_aux_b"/><![CDATA[ ]]><fbt_token name="sent_aux_c"/><![CDATA[.]]></fbt_text>
  </fbt_string>
  <fbt_string locale="en_US" hash="a84aae4eb08ccc9ba88a1d64ef7a185a">
    <fbt_text><fbt_token name="name1"/><![CDATA[ and ]]><fbt_token name="name count others"/><![CDATA[ had ]]><fbt_token name="product1"/><![CDATA[.]]></fbt_text>
  </fbt_string>
  <fbt_string locale="en_US" hash="ac8648780516740b4e8c126ce37eda2c">
    <fbt_text><fbt_token name="name"/><![CDATA[ had a product ]]><fbt_token name="sent_aux_a"/><![CDATA[ ]]><fbt_token name="sent_aux_b"/><![CDATA[ ]]><fbt_token name="sent_aux_c"/><![CDATA[.]]></fbt_text>
  </fbt_string>
  <fbt_string locale="en_US" hash="ad56f17f94e566614748aad3ac52c055">
    <fbt_text><![CDATA[You and ]]><fbt_token name="name1"/><![CDATA[ had this.]]></fbt_text>
  </fbt_string>
  <fbt_string locale="en_US" hash="b40416f0e840a44a4923862bac98cae9">
    <fbt_text><fbt_token name="name1"/><![CDATA[ had ]]><fbt_token name="product1"/><![CDATA[ and ]]><fbt_token name="product2"/><![CDATA[.]]></fbt_text>
  </fbt_string>
  <fbt_string locale="en_US" hash="b43580c1d8772052f87f7fd63807b456">
    <fbt_text><fbt_token name="name1"/><![CDATA[ had a product.]]></fbt_text>
  </fbt_string>
  <fbt_string locale="en_US" hash="bfe0261551921e4cfbdcbe1132966a0f">
    <fbt_text><fbt_token name="name1"/><![CDATA[ had ]]><fbt_token name="product1"/><![CDATA[ and ]]><fbt_token name="product count other products"/><![CDATA[.]]></fbt_text>
  </fbt_string>
  <fbt_string locale="en_US" hash="c5837e9a510c1dde0dcdd3ad6e5b636a">
    <fbt_text><fbt_token name="name1"/><![CDATA[ and ]]><fbt_token name="name2"/><![CDATA[ had ]]><fbt_token name="product1"/><![CDATA[ and ]]><fbt_token name="product count other products"/><![CDATA[.]]></fbt_text>
  </fbt_string>
  <fbt_string locale="en_US" hash="c74e35339e477c0dbe9fb3ca52cd841d">
    <fbt_text><fbt_token name="name1"/><![CDATA[ had ]]><fbt_token name="product1"/><![CDATA[.]]></fbt_text>
  </fbt_string>
  <fbt_string locale="en_US" hash="cd434eb4752351ed2a062d83b00b3774">
    <fbt_text><fbt_token name="name1"/><![CDATA[ and ]]><fbt_token name="name2"/><![CDATA[ had ]]><fbt_token name="product1"/><![CDATA[.]]></fbt_text>
  </fbt_string>
  <fbt_string locale="en_US" hash="cf3d566617a239df708321a5266dd014">
    <fbt_text><![CDATA[a product she had]]></fbt_text>
  </fbt_string>
  <fbt_string locale="en_US" hash="d0fd8bde66e23e0c19853b8e3b22b405">
    <fbt_text><![CDATA[products you had]]></fbt_text>
  </fbt_string>
  <fbt_string locale="en_US" hash="d512aea0c2b2f679d54895fb8d95575f">
    <fbt_text><fbt_token name="name1"/><![CDATA[ and ]]><fbt_token name="name2"/><![CDATA[ had ]]><fbt_token name="product count products"/><![CDATA[ ]]><fbt_token name="sent_aux_a"/><![CDATA[ ]]><fbt_token name="sent_aux_b"/><![CDATA[ ]]><fbt_token name="sent_aux_c"/><![CDATA[.]]></fbt_text>
  </fbt_string>
  <fbt_string locale="en_US" hash="e0139bc382f676868fe47c21410cab99">
    <fbt_text><fbt_token name="name1"/><![CDATA[ had ]]><fbt_token name="product1"/><![CDATA[ and ]]><fbt_token name="product2"/><![CDATA[ ]]><fbt_token name="sent_aux_a"/><![CDATA[ ]]><fbt_token name="sent_aux_b"/><![CDATA[ ]]><fbt_token name="sent_aux_c"/><![CDATA[.]]></fbt_text>
  </fbt_string>
  <fbt_string locale="en_US" hash="e16580eef1aee24267ecddc159d6045e">
    <fbt_text><fbt_token name="name1"/><![CDATA[ and ]]><fbt_token name="name2"/><![CDATA[ had a product.]]></fbt_text>
  </fbt_string>
  <fbt_string locale="en_US" hash="ea0f59a9dd139620176cc3725f0cc9c6">
    <fbt_text><fbt_token name="name1"/><![CDATA[ had ]]><fbt_token name="product count products"/><![CDATA[.]]></fbt_text>
  </fbt_string>
  <fbt_string locale="en_US" hash="ee98296039c6a1aef5849899bf2665d9">
    <fbt_text><fbt_token name="name1"/><![CDATA[ had ]]><fbt_token name="product1"/><![CDATA[ and ]]><fbt_token name="product count other products"/><![CDATA[ ]]><fbt_token name="sent_aux_a"/><![CDATA[ ]]><fbt_token name="sent_aux_b"/><![CDATA[ ]]><fbt_token name="sent_aux_c"/><![CDATA[.]]></fbt_text>
  </fbt_string>
  <fbt_string locale="en_US" hash="fcceddb3c4a5f8fddc2fab9fbc8c1390">
    <fbt_text><fbt_token name="number"/><![CDATA[ others had this.]]></fbt_text>
  </fbt_string>
</fbt_app>
